{
    "Version": "1.2",
    "Data": {
        "Source": "d:\\code\\aith_unreal\\plugins\\developer\\riderlink\\source\\rd\\src\\rd_gen_cpp\\src\\rdtextbuffer.cpp",
        "ProvidedModule": "",
        "Includes": [
            "d:\\code\\aith_unreal\\plugins\\developer\\riderlink\\intermediate\\build\\win64\\x64\\unrealeditor\\development\\rd\\definitions.h",
            "d:\\code\\aith_unreal\\plugins\\developer\\riderlink\\source\\rd\\src\\rd_gen_cpp\\src\\rdtextbuffer.h"
        ],
        "ImportedModules": [],
        "ImportedHeaderUnits": []
    }
}